{
	"requirement": [
		{
			"ident":"1",
			"name":"ELIZABETH"
		},
		{
			"ident":"2",
			"name":"TERRI"
		},
		{
			"ident":"3",
			"name":"JOHNNY"
		},
		{
			"ident":"4",
			"name":"ROSE"
		},
		{
			"ident":"5",
			"name":"RICK"
		},
		{
			"ident":"6",
			"name":"CAROL"
		},
		{
			"ident":"7",
			"name":"HERBERT"
		},
		{
			"ident":"8",
			"name":"CHARLENE"
		},
		{
			"ident":"9",
			"name":"LEN"
		},
		{
			"ident":"10",
			"name":"CRISTOBAL"
		},
		{
			"ident":"11",
			"name":"NORMA"
		},
		{
			"ident":"12",
			"name":"JANICE"
		},
		{
			"ident":"13",
			"name":"VERNON"
		},
		{
			"ident":"14",
			"name":"DONALD"
		},
		{
			"ident":"15",
			"name":"JOANNE"
		},
		{
			"ident":"16",
			"name":"MAUREEN"
		},
		{
			"ident":"17",
			"name":"JOANNE"
		},
		{
			"ident":"18",
			"name":"ERNEST"
		},
		{
			"ident":"19",
			"name":"JOHNNY"
		},
		{
			"ident":"20",
			"name":"BEVERLY"
		},
		{
			"ident":"21",
			"name":"CARMEN"
		},
		{
			"ident":"22",
			"name":"GERALDINE"
		},
		{
			"ident":"23",
			"name":"GINA"
		},
		{
			"ident":"24",
			"name":"LORI"
		},
		{
			"ident":"25",
			"name":"SEAN"
		},
		{
			"ident":"26",
			"name":"HAROLD"
		},
		{
			"ident":"27",
			"name":"MICHELLE"
		},
		{
			"ident":"28",
			"name":"KRISTIN"
		},
		{
			"ident":"29",
			"name":"STACEY"
		},
		{
			"ident":"30",
			"name":"WILMA"
		},
		{
			"ident":"31",
			"name":"FRANCIS"
		},
		{
			"ident":"32",
			"name":"BRITT"
		},
		{
			"ident":"33",
			"name":"ANITA"
		},
		{
			"ident":"34",
			"name":"SUE"
		},
		{
			"ident":"35",
			"name":"KRISTIN"
		},
		{
			"ident":"36",
			"name":"EVELYN"
		},
		{
			"ident":"37",
			"name":"BETH"
		},
		{
			"ident":"38",
			"name":"TROY"
		},
		{
			"ident":"39",
			"name":"RUBY"
		},
		{
			"ident":"40",
			"name":"DOROTHY"
		},
		{
			"ident":"41",
			"name":"TIMOTHY"
		},
		{
			"ident":"42",
			"name":"TONEY"
		},
		{
			"ident":"43",
			"name":"STEPHEN"
		},
		{
			"ident":"44",
			"name":"RICARDO"
		},
		{
			"ident":"45",
			"name":"BETTY"
		},
		{
			"ident":"46",
			"name":"ANN"
		},
		{
			"ident":"47",
			"name":"DENISE"
		},
		{
			"ident":"48",
			"name":"LEWIS"
		},
		{
			"ident":"49",
			"name":"ALEXANDER"
		},
		{
			"ident":"50",
			"name":"MICHELE"
		},
		{
			"ident":"51",
			"name":"BESSIE"
		},
		{
			"ident":"52",
			"name":"RAYFORD"
		},
		{
			"ident":"53",
			"name":"LINDA"
		},
		{
			"ident":"54",
			"name":"JAROD"
		},
		{
			"ident":"55",
			"name":"CURTIS"
		},
		{
			"ident":"56",
			"name":"DEL"
		},
		{
			"ident":"57",
			"name":"LUIS"
		},
		{
			"ident":"58",
			"name":"SARAH"
		},
		{
			"ident":"59",
			"name":"ANGELA"
		},
		{
			"ident":"60",
			"name":"CHRISTOPHER"
		},
		{
			"ident":"61",
			"name":"MICHELE"
		},
		{
			"ident":"62",
			"name":"STACY"
		},
		{
			"ident":"63",
			"name":"JERRY"
		},
		{
			"ident":"64",
			"name":"HEATHER"
		},
		{
			"ident":"65",
			"name":"MELISSA"
		},
		{
			"ident":"66",
			"name":"MIKE"
		},
		{
			"ident":"67",
			"name":"JAMES"
		},
		{
			"ident":"68",
			"name":"BERTHA"
		},
		{
			"ident":"69",
			"name":"TRACY"
		},
		{
			"ident":"70",
			"name":"KATHY"
		},
		{
			"ident":"71",
			"name":"LUCILLE"
		},
		{
			"ident":"72",
			"name":"LILLIAN"
		},
		{
			"ident":"73",
			"name":"JOANN"
		},
		{
			"ident":"74",
			"name":"CARL"
		},
		{
			"ident":"75",
			"name":"ALICIA"
		},
		{
			"ident":"76",
			"name":"ERIC"
		},
		{
			"ident":"77",
			"name":"RICK"
		},
		{
			"ident":"78",
			"name":"MICHELLE"
		},
		{
			"ident":"79",
			"name":"ROBERTO"
		},
		{
			"ident":"80",
			"name":"SHIRLEY"
		},
		{
			"ident":"81",
			"name":"SYLVIA"
		},
		{
			"ident":"82",
			"name":"BRUCE"
		},
		{
			"ident":"83",
			"name":"ROSE"
		},
		{
			"ident":"84",
			"name":"EILEEN"
		},
		{
			"ident":"85",
			"name":"ELIZABETH"
		},
		{
			"ident":"86",
			"name":"EMILY"
		},
		{
			"ident":"87",
			"name":"DOUGLASS"
		},
		{
			"ident":"88",
			"name":"MILAN"
		},
		{
			"ident":"89",
			"name":"EUGENE"
		},
		{
			"ident":"90",
			"name":"ARLENE"
		},
		{
			"ident":"91",
			"name":"JUANITA"
		},
		{
			"ident":"92",
			"name":"SAMUEL"
		},
		{
			"ident":"93",
			"name":"JESSIE"
		},
		{
			"ident":"94",
			"name":"BENEDICT"
		},
		{
			"ident":"95",
			"name":"HENRY"
		},
		{
			"ident":"96",
			"name":"JANICE"
		},
		{
			"ident":"97",
			"name":"MANUEL"
		},
		{
			"ident":"98",
			"name":"JUSTIN"
		},
		{
			"ident":"99",
			"name":"PAMELA"
		},
		{
			"ident":"100",
			"name":"MARJORIE"
		},
		{
			"ident":"101",
			"name":"ELIZABETH"
		},
		{
			"ident":"102",
			"name":"MARJORIE"
		},
		{
			"ident":"103",
			"name":"JUDY"
		},
		{
			"ident":"104",
			"name":"DENNIS"
		},
		{
			"ident":"105",
			"name":"HELEN"
		},
		{
			"ident":"106",
			"name":"RAYFORD"
		},
		{
			"ident":"107",
			"name":"ERASMO"
		},
		{
			"ident":"108",
			"name":"RICKY"
		},
		{
			"ident":"109",
			"name":"ERASMO"
		},
		{
			"ident":"110",
			"name":"REGINALD"
		},
		{
			"ident":"111",
			"name":"JEFF"
		},
		{
			"ident":"112",
			"name":"HECTOR"
		},
		{
			"ident":"113",
			"name":"DERRICK"
		},
		{
			"ident":"114",
			"name":"BRITT"
		},
		{
			"ident":"115",
			"name":"ANGEL"
		},
		{
			"ident":"116",
			"name":"ANNETTE"
		},
		{
			"ident":"117",
			"name":"BEVERLY"
		},
		{
			"ident":"118",
			"name":"BARRY"
		},
		{
			"ident":"119",
			"name":"JESSE"
		},
		{
			"ident":"120",
			"name":"KATHLEEN"
		},
		{
			"ident":"121",
			"name":"ANNE"
		},
		{
			"ident":"122",
			"name":"MICHELE"
		},
		{
			"ident":"123",
			"name":"KELLY"
		},
		{
			"ident":"124",
			"name":"RICHARD"
		},
		{
			"ident":"125",
			"name":"LEON"
		},
		{
			"ident":"126",
			"name":"STEPHEN"
		},
		{
			"ident":"127",
			"name":"DOUGLASS"
		},
		{
			"ident":"128",
			"name":"DOUGLASS"
		},
		{
			"ident":"129",
			"name":"ALICIA"
		},
		{
			"ident":"130",
			"name":"RANDALL"
		},
		{
			"ident":"131",
			"name":"JANE"
		},
		{
			"ident":"132",
			"name":"JANICE"
		},
		{
			"ident":"133",
			"name":"CARRIE"
		},
		{
			"ident":"134",
			"name":"DOLORES"
		},
		{
			"ident":"135",
			"name":"CATHERINE"
		},
		{
			"ident":"136",
			"name":"ROBERTO"
		},
		{
			"ident":"137",
			"name":"ROGER"
		},
		{
			"ident":"138",
			"name":"WALTON"
		},
		{
			"ident":"139",
			"name":"JUDY"
		},
		{
			"ident":"140",
			"name":"BRUCE"
		},
		{
			"ident":"141",
			"name":"ANA"
		},
		{
			"ident":"142",
			"name":"NORMAN"
		},
		{
			"ident":"143",
			"name":"STEVE"
		},
		{
			"ident":"144",
			"name":"CHRIS"
		},
		{
			"ident":"145",
			"name":"LUCILLE"
		},
		{
			"ident":"146",
			"name":"RACHEL"
		},
		{
			"ident":"147",
			"name":"TRACY"
		},
		{
			"ident":"148",
			"name":"RUTH"
		},
		{
			"ident":"149",
			"name":"BARRY"
		},
		{
			"ident":"150",
			"name":"JUDE"
		},
		{
			"ident":"151",
			"name":"LEONARD"
		},
		{
			"ident":"152",
			"name":"ALEX"
		},
		{
			"ident":"153",
			"name":"ROBERTO"
		},
		{
			"ident":"154",
			"name":"DAVID"
		},
		{
			"ident":"155",
			"name":"NORMA"
		},
		{
			"ident":"156",
			"name":"LAURA"
		},
		{
			"ident":"157",
			"name":"GERTRUDE"
		},
		{
			"ident":"158",
			"name":"SHAWN"
		},
		{
			"ident":"159",
			"name":"ELSIE"
		},
		{
			"ident":"160",
			"name":"KAREN"
		},
		{
			"ident":"161",
			"name":"BRETT"
		},
		{
			"ident":"162",
			"name":"THERESA"
		},
		{
			"ident":"163",
			"name":"MICHELLE"
		},
		{
			"ident":"164",
			"name":"DON"
		},
		{
			"ident":"165",
			"name":"HECTOR"
		},
		{
			"ident":"166",
			"name":"LUCY"
		},
		{
			"ident":"167",
			"name":"LOUISE"
		},
		{
			"ident":"168",
			"name":"STANLEY"
		},
		{
			"ident":"169",
			"name":"NORMAN"
		},
		{
			"ident":"170",
			"name":"TONY"
		},
		{
			"ident":"171",
			"name":"VINCENT"
		},
		{
			"ident":"172",
			"name":"JORGE"
		},
		{
			"ident":"173",
			"name":"RACHEL"
		},
		{
			"ident":"174",
			"name":"JUDE"
		},
		{
			"ident":"175",
			"name":"PAULA"
		},
		{
			"ident":"176",
			"name":"DOUGLAS"
		},
		{
			"ident":"177",
			"name":"SUZANNE"
		},
		{
			"ident":"178",
			"name":"BENJAMIN"
		},
		{
			"ident":"179",
			"name":"CHARLOTTE"
		},
		{
			"ident":"180",
			"name":"LEE"
		},
		{
			"ident":"181",
			"name":"SCOTT"
		},
		{
			"ident":"182",
			"name":"BRENDA"
		},
		{
			"ident":"183",
			"name":"ROBERTO"
		},
		{
			"ident":"184",
			"name":"GRACE"
		},
		{
			"ident":"185",
			"name":"GLEN"
		},
		{
			"ident":"186",
			"name":"MELINDA"
		},
		{
			"ident":"187",
			"name":"JULIE"
		},
		{
			"ident":"188",
			"name":"SUZANNE"
		},
		{
			"ident":"189",
			"name":"GREGORY"
		},
		{
			"ident":"190",
			"name":"MEGAN"
		},
		{
			"ident":"191",
			"name":"MARION"
		},
		{
			"ident":"192",
			"name":"DELORES"
		},
		{
			"ident":"193",
			"name":"EDDIE"
		},
		{
			"ident":"194",
			"name":"DENNIS"
		},
		{
			"ident":"195",
			"name":"ALEXANDER"
		},
		{
			"ident":"196",
			"name":"GINA"
		},
		{
			"ident":"197",
			"name":"GENE"
		},
		{
			"ident":"198",
			"name":"DEBBIE"
		},
		{
			"ident":"199",
			"name":"GREGORY"
		},
		{
			"ident":"200",
			"name":"SEAN"
		},
		{
			"ident":"201",
			"name":"BRUCE"
		},
		{
			"ident":"202",
			"name":"CHAD"
		},
		{
			"ident":"203",
			"name":"JACK"
		},
		{
			"ident":"204",
			"name":"RONNIE"
		},
		{
			"ident":"205",
			"name":"SHERWOOD"
		},
		{
			"ident":"206",
			"name":"FRANCISCO"
		},
		{
			"ident":"207",
			"name":"ANN"
		},
		{
			"ident":"208",
			"name":"JOSEPHINE"
		},
		{
			"ident":"209",
			"name":"OSWALDO"
		},
		{
			"ident":"210",
			"name":"JOHN"
		},
		{
			"ident":"211",
			"name":"JOHNNY"
		},
		{
			"ident":"212",
			"name":"HENRY"
		},
		{
			"ident":"213",
			"name":"CAROLYN"
		},
		{
			"ident":"214",
			"name":"STACEY"
		},
		{
			"ident":"215",
			"name":"JOHN"
		},
		{
			"ident":"216",
			"name":"CLARA"
		},
		{
			"ident":"217",
			"name":"TYLER"
		},
		{
			"ident":"218",
			"name":"PHILIP"
		},
		{
			"ident":"219",
			"name":"SAMUEL"
		},
		{
			"ident":"220",
			"name":"TIM"
		},
		{
			"ident":"221",
			"name":"WANDA"
		},
		{
			"ident":"222",
			"name":"ANNETTE"
		},
		{
			"ident":"223",
			"name":"CAROLYN"
		},
		{
			"ident":"224",
			"name":"ESTHER"
		},
		{
			"ident":"225",
			"name":"BENEDICT"
		},
		{
			"ident":"226",
			"name":"RICHARD"
		},
		{
			"ident":"227",
			"name":"BARRY"
		},
		{
			"ident":"228",
			"name":"JESSIE"
		},
		{
			"ident":"229",
			"name":"MILAN"
		},
		{
			"ident":"230",
			"name":"TIMOTHY"
		},
		{
			"ident":"231",
			"name":"JORGE"
		},
		{
			"ident":"232",
			"name":"GLADYS"
		},
		{
			"ident":"233",
			"name":"GERALDINE"
		},
		{
			"ident":"234",
			"name":"WALTON"
		},
		{
			"ident":"235",
			"name":"GRACE"
		},
		{
			"ident":"236",
			"name":"WILLIAM"
		},
		{
			"ident":"237",
			"name":"KELLY"
		},
		{
			"ident":"238",
			"name":"JAROD"
		},
		{
			"ident":"239",
			"name":"TRACY"
		},
		{
			"ident":"240",
			"name":"GRACE"
		},
		{
			"ident":"241",
			"name":"JEREMY"
		},
		{
			"ident":"242",
			"name":"CARLOS"
		},
		{
			"ident":"243",
			"name":"BRENT"
		},
		{
			"ident":"244",
			"name":"STACY"
		},
		{
			"ident":"245",
			"name":"JUAN"
		},
		{
			"ident":"246",
			"name":"STEVE"
		},
		{
			"ident":"247",
			"name":"CURTIS"
		},
		{
			"ident":"248",
			"name":"HERMAN"
		},
		{
			"ident":"249",
			"name":"CHARLIE"
		},
		{
			"ident":"250",
			"name":"CAROLYN"
		},
		{
			"ident":"251",
			"name":"SUZANNE"
		},
		{
			"ident":"252",
			"name":"ALEX"
		},
		{
			"ident":"253",
			"name":"LUCILLE"
		},
		{
			"ident":"254",
			"name":"MARJORIE"
		},
		{
			"ident":"255",
			"name":"MARTIN"
		},
		{
			"ident":"256",
			"name":"CRYSTAL"
		},
		{
			"ident":"257",
			"name":"JANICE"
		},
		{
			"ident":"258",
			"name":"LAWRENCE"
		},
		{
			"ident":"259",
			"name":"DERRICK"
		},
		{
			"ident":"260",
			"name":"STEVE"
		},
		{
			"ident":"261",
			"name":"BENEDICT"
		},
		{
			"ident":"262",
			"name":"TOMMY"
		},
		{
			"ident":"263",
			"name":"LORRAINE"
		},
		{
			"ident":"264",
			"name":"RAMON"
		},
		{
			"ident":"265",
			"name":"JESSIE"
		},
		{
			"ident":"266",
			"name":"EUGENE"
		},
		{
			"ident":"267",
			"name":"MOSE"
		},
		{
			"ident":"268",
			"name":"CRYSTAL"
		},
		{
			"ident":"269",
			"name":"ERIC"
		},
		{
			"ident":"270",
			"name":"BENEDICT"
		},
		{
			"ident":"271",
			"name":"EILEEN"
		},
		{
			"ident":"272",
			"name":"NATHAN"
		},
		{
			"ident":"273",
			"name":"ALBERT"
		},
		{
			"ident":"274",
			"name":"VALERIE"
		},
		{
			"ident":"275",
			"name":"GORDON"
		},
		{
			"ident":"276",
			"name":"GORDON"
		},
		{
			"ident":"277",
			"name":"RICARDO"
		},
		{
			"ident":"278",
			"name":"ROSA"
		},
		{
			"ident":"279",
			"name":"VICKI"
		},
		{
			"ident":"280",
			"name":"GERALDINE"
		},
		{
			"ident":"281",
			"name":"CLYDE"
		},
		{
			"ident":"282",
			"name":"LLOYD"
		},
		{
			"ident":"283",
			"name":"FLORENCE"
		},
		{
			"ident":"284",
			"name":"RACHEL"
		},
		{
			"ident":"285",
			"name":"MARC"
		},
		{
			"ident":"286",
			"name":"BERNICE"
		},
		{
			"ident":"287",
			"name":"BRIAN"
		},
		{
			"ident":"288",
			"name":"JAMIE"
		},
		{
			"ident":"289",
			"name":"APRIL"
		},
		{
			"ident":"290",
			"name":"PAULA"
		},
		{
			"ident":"291",
			"name":"SHAWN"
		},
		{
			"ident":"292",
			"name":"JOE"
		},
		{
			"ident":"293",
			"name":"EZEQUIEL"
		},
		{
			"ident":"294",
			"name":"ANGEL"
		},
		{
			"ident":"295",
			"name":"ALICIA"
		},
		{
			"ident":"296",
			"name":"KRISTIN"
		},
		{
			"ident":"297",
			"name":"ROGER"
		},
		{
			"ident":"298",
			"name":"SHERWOOD"
		},
		{
			"ident":"299",
			"name":"RANDALL"
		},
		{
			"ident":"300",
			"name":"MARY"
		},
		{
			"ident":"301",
			"name":"KATHLEEN"
		},
		{
			"ident":"302",
			"name":"DEREK"
		},
		{
			"ident":"303",
			"name":"TITUS"
		},
		{
			"ident":"304",
			"name":"BERTHA"
		},
		{
			"ident":"305",
			"name":"ROY"
		},
		{
			"ident":"306",
			"name":"DALE"
		},
		{
			"ident":"307",
			"name":"RALPH"
		},
		{
			"ident":"308",
			"name":"LYNN"
		},
		{
			"ident":"309",
			"name":"MARCUS"
		},
		{
			"ident":"310",
			"name":"NANCY"
		},
		{
			"ident":"311",
			"name":"RUBY"
		},
		{
			"ident":"312",
			"name":"CHARLIE"
		},
		{
			"ident":"313",
			"name":"VICKI"
		},
		{
			"ident":"314",
			"name":"TIMOTHY"
		},
		{
			"ident":"315",
			"name":"JON"
		},
		{
			"ident":"316",
			"name":"CARLA"
		},
		{
			"ident":"317",
			"name":"VIRGILIO"
		},
		{
			"ident":"318",
			"name":"LINO"
		},
		{
			"ident":"319",
			"name":"WALTER"
		},
		{
			"ident":"320",
			"name":"KIMBERLY"
		},
		{
			"ident":"321",
			"name":"KAREN"
		},
		{
			"ident":"322",
			"name":"BEATRICE"
		},
		{
			"ident":"323",
			"name":"BEVERLY"
		},
		{
			"ident":"324",
			"name":"CORDELL"
		},
		{
			"ident":"325",
			"name":"DANA"
		},
		{
			"ident":"326",
			"name":"MARCUS"
		},
		{
			"ident":"327",
			"name":"GERALDINE"
		},
		{
			"ident":"328",
			"name":"CHRISTINE"
		},
		{
			"ident":"329",
			"name":"ALLEN"
		},
		{
			"ident":"330",
			"name":"KIM"
		},
		{
			"ident":"331",
			"name":"LORI"
		},
		{
			"ident":"332",
			"name":"BEVERLY"
		},
		{
			"ident":"333",
			"name":"ELLSWORTH"
		},
		{
			"ident":"334",
			"name":"WILMA"
		},
		{
			"ident":"335",
			"name":"ANNA"
		},
		{
			"ident":"336",
			"name":"LINO"
		},
		{
			"ident":"337",
			"name":"MARC"
		},
		{
			"ident":"338",
			"name":"ANN"
		},
		{
			"ident":"339",
			"name":"TIM"
		},
		{
			"ident":"340",
			"name":"ANTHONY"
		},
		{
			"ident":"341",
			"name":"JEFFERY"
		},
		{
			"ident":"342",
			"name":"VERA"
		},
		{
			"ident":"343",
			"name":"NATHAN"
		},
		{
			"ident":"344",
			"name":"CALVIN"
		},
		{
			"ident":"345",
			"name":"BONNIE"
		},
		{
			"ident":"346",
			"name":"ANDREA"
		},
		{
			"ident":"347",
			"name":"GAIL"
		},
		{
			"ident":"348",
			"name":"SUZANNE"
		},
		{
			"ident":"349",
			"name":"LEO"
		},
		{
			"ident":"350",
			"name":"JESUS"
		},
		{
			"ident":"351",
			"name":"LILLIAN"
		},
		{
			"ident":"352",
			"name":"LUCY"
		},
		{
			"ident":"353",
			"name":"HERB"
		},
		{
			"ident":"354",
			"name":"KRISTIN"
		},
		{
			"ident":"355",
			"name":"HARRY"
		},
		{
			"ident":"356",
			"name":"TIM"
		},
		{
			"ident":"357",
			"name":"BEVERLY"
		},
		{
			"ident":"358",
			"name":"LEE"
		},
		{
			"ident":"359",
			"name":"PEARL"
		},
		{
			"ident":"360",
			"name":"JON"
		},
		{
			"ident":"361",
			"name":"MARY"
		},
		{
			"ident":"362",
			"name":"CRAIG"
		},
		{
			"ident":"363",
			"name":"BRYAN"
		},
		{
			"ident":"364",
			"name":"OSCAR"
		},
		{
			"ident":"365",
			"name":"PEGGY"
		},
		{
			"ident":"366",
			"name":"GINA"
		},
		{
			"ident":"367",
			"name":"ANA"
		},
		{
			"ident":"368",
			"name":"KEITH"
		},
		{
			"ident":"369",
			"name":"BENEDICT"
		},
		{
			"ident":"370",
			"name":"RANDY"
		},
		{
			"ident":"371",
			"name":"STANLEY"
		},
		{
			"ident":"372",
			"name":"ANN"
		},
		{
			"ident":"373",
			"name":"JONATHAN"
		},
		{
			"ident":"374",
			"name":"BARRY"
		},
		{
			"ident":"375",
			"name":"CARLOS"
		},
		{
			"ident":"376",
			"name":"LAURA"
		},
		{
			"ident":"377",
			"name":"STEVE"
		},
		{
			"ident":"378",
			"name":"MARIE"
		},
		{
			"ident":"379",
			"name":"ELIZABETH"
		},
		{
			"ident":"380",
			"name":"LUIS"
		},
		{
			"ident":"381",
			"name":"LEROY"
		},
		{
			"ident":"382",
			"name":"CLARA"
		},
		{
			"ident":"383",
			"name":"LOIS"
		},
		{
			"ident":"384",
			"name":"VERNON"
		},
		{
			"ident":"385",
			"name":"DOLORES"
		},
		{
			"ident":"386",
			"name":"PAULINE"
		},
		{
			"ident":"387",
			"name":"KELLY"
		},
		{
			"ident":"388",
			"name":"FLORENCE"
		},
		{
			"ident":"389",
			"name":"NATALIE"
		},
		{
			"ident":"390",
			"name":"ROGER"
		},
		{
			"ident":"391",
			"name":"PALMER"
		},
		{
			"ident":"392",
			"name":"BETH"
		},
		{
			"ident":"393",
			"name":"DERRICK"
		},
		{
			"ident":"394",
			"name":"PHILLIP"
		},
		{
			"ident":"395",
			"name":"WARREN"
		},
		{
			"ident":"396",
			"name":"LLOYD"
		},
		{
			"ident":"397",
			"name":"ROY"
		},
		{
			"ident":"398",
			"name":"PAULINE"
		},
		{
			"ident":"399",
			"name":"MICHEAL"
		},
		{
			"ident":"400",
			"name":"JENNIFER"
		},
		{
			"ident":"401",
			"name":"RONALD"
		},
		{
			"ident":"402",
			"name":"BRITT"
		},
		{
			"ident":"403",
			"name":"KATHY"
		},
		{
			"ident":"404",
			"name":"SHARON"
		},
		{
			"ident":"405",
			"name":"DEBRA"
		},
		{
			"ident":"406",
			"name":"BENEDICT"
		},
		{
			"ident":"407",
			"name":"ERICA"
		},
		{
			"ident":"408",
			"name":"MARCUS"
		},
		{
			"ident":"409",
			"name":"JAMIE"
		},
		{
			"ident":"410",
			"name":"ANITA"
		},
		{
			"ident":"411",
			"name":"LEO"
		},
		{
			"ident":"412",
			"name":"ANNETTE"
		},
		{
			"ident":"413",
			"name":"RAYFORD"
		},
		{
			"ident":"414",
			"name":"GENE"
		},
		{
			"ident":"415",
			"name":"DEREK"
		},
		{
			"ident":"416",
			"name":"BERNICE"
		},
		{
			"ident":"417",
			"name":"DENNIS"
		},
		{
			"ident":"418",
			"name":"JANICE"
		},
		{
			"ident":"419",
			"name":"MELINDA"
		},
		{
			"ident":"420",
			"name":"DALE"
		},
		{
			"ident":"421",
			"name":"EDNA"
		},
		{
			"ident":"422",
			"name":"JESUS"
		},
		{
			"ident":"423",
			"name":"NATHAN"
		},
		{
			"ident":"424",
			"name":"TITUS"
		},
		{
			"ident":"425",
			"name":"JEFFREY"
		},
		{
			"ident":"426",
			"name":"CLARENCE"
		},
		{
			"ident":"427",
			"name":"DORIS"
		},
		{
			"ident":"428",
			"name":"MARIA"
		},
		{
			"ident":"429",
			"name":"ANGEL"
		},
		{
			"ident":"430",
			"name":"EMILY"
		},
		{
			"ident":"431",
			"name":"JESSIE"
		},
		{
			"ident":"432",
			"name":"CARLOS"
		},
		{
			"ident":"433",
			"name":"CURTIS"
		},
		{
			"ident":"434",
			"name":"ANN"
		},
		{
			"ident":"435",
			"name":"FRANCES"
		},
		{
			"ident":"436",
			"name":"ANNE"
		},
		{
			"ident":"437",
			"name":"STANTON"
		},
		{
			"ident":"438",
			"name":"FLORENCE"
		},
		{
			"ident":"439",
			"name":"GREGORY"
		},
		{
			"ident":"440",
			"name":"EDWIN"
		},
		{
			"ident":"441",
			"name":"WILLIE"
		},
		{
			"ident":"442",
			"name":"JESSE"
		},
		{
			"ident":"443",
			"name":"JOHN"
		},
		{
			"ident":"444",
			"name":"MARJORIE"
		},
		{
			"ident":"445",
			"name":"EARL"
		},
		{
			"ident":"446",
			"name":"JON"
		},
		{
			"ident":"447",
			"name":"SHANE"
		},
		{
			"ident":"448",
			"name":"PAMELA"
		},
		{
			"ident":"449",
			"name":"BENEDICT"
		},
		{
			"ident":"450",
			"name":"LEON"
		},
		{
			"ident":"451",
			"name":"BERNARD"
		},
		{
			"ident":"452",
			"name":"VIRGINIA"
		},
		{
			"ident":"453",
			"name":"ANNA"
		},
		{
			"ident":"454",
			"name":"RITA"
		},
		{
			"ident":"455",
			"name":"JANE"
		},
		{
			"ident":"456",
			"name":"KATHRYN"
		},
		{
			"ident":"457",
			"name":"SAMANTHA"
		},
		{
			"ident":"458",
			"name":"ANTHONY"
		},
		{
			"ident":"459",
			"name":"JUDY"
		},
		{
			"ident":"460",
			"name":"CRYSTAL"
		},
		{
			"ident":"461",
			"name":"TOM"
		},
		{
			"ident":"462",
			"name":"JESSICA"
		},
		{
			"ident":"463",
			"name":"JEAN"
		},
		{
			"ident":"464",
			"name":"ALEX"
		},
		{
			"ident":"465",
			"name":"WILLIE"
		},
		{
			"ident":"466",
			"name":"BETTY"
		},
		{
			"ident":"467",
			"name":"ERNEST"
		},
		{
			"ident":"468",
			"name":"CHARLOTTE"
		},
		{
			"ident":"469",
			"name":"RANDALL"
		},
		{
			"ident":"470",
			"name":"CHRISTOPHER"
		},
		{
			"ident":"471",
			"name":"JAMIE"
		},
		{
			"ident":"472",
			"name":"GERALDINE"
		},
		{
			"ident":"473",
			"name":"BETH"
		},
		{
			"ident":"474",
			"name":"DONALD"
		},
		{
			"ident":"475",
			"name":"GERALD"
		},
		{
			"ident":"476",
			"name":"LAUREN"
		},
		{
			"ident":"477",
			"name":"CORDELL"
		},
		{
			"ident":"478",
			"name":"JESSICA"
		},
		{
			"ident":"479",
			"name":"CATHY"
		},
		{
			"ident":"480",
			"name":"ROBIN"
		},
		{
			"ident":"481",
			"name":"TOM"
		},
		{
			"ident":"482",
			"name":"VICTORIA"
		},
		{
			"ident":"483",
			"name":"CLYDE"
		},
		{
			"ident":"484",
			"name":"ELAINE"
		},
		{
			"ident":"485",
			"name":"LUCY"
		},
		{
			"ident":"486",
			"name":"RACHEL"
		},
		{
			"ident":"487",
			"name":"EDITH"
		},
		{
			"ident":"488",
			"name":"LLOYD"
		},
		{
			"ident":"489",
			"name":"BRITT"
		},
		{
			"ident":"490",
			"name":"VERNON"
		},
		{
			"ident":"491",
			"name":"KELLY"
		},
		{
			"ident":"492",
			"name":"NORMAN"
		},
		{
			"ident":"493",
			"name":"JEREMY"
		},
		{
			"ident":"494",
			"name":"JORGE"
		},
		{
			"ident":"495",
			"name":"GERALDINE"
		},
		{
			"ident":"496",
			"name":"RICARDO"
		},
		{
			"ident":"497",
			"name":"THERESA"
		},
		{
			"ident":"498",
			"name":"ELSIE"
		},
		{
			"ident":"499",
			"name":"JUDE"
		},
		{
			"ident":"500",
			"name":"FLOYD"
		},
		{
			"ident":"501",
			"name":"AMY"
		},
		{
			"ident":"502",
			"name":"LARRY"
		},
		{
			"ident":"503",
			"name":"JAY"
		},
		{
			"ident":"504",
			"name":"MELINDA"
		},
		{
			"ident":"505",
			"name":"WENDY"
		},
		{
			"ident":"506",
			"name":"LORI"
		},
		{
			"ident":"507",
			"name":"CHRIS"
		},
		{
			"ident":"508",
			"name":"ALMA"
		},
		{
			"ident":"509",
			"name":"HEATHER"
		},
		{
			"ident":"510",
			"name":"JORGE"
		},
		{
			"ident":"511",
			"name":"LUIS"
		},
		{
			"ident":"512",
			"name":"HYMAN"
		},
		{
			"ident":"513",
			"name":"KEITH"
		},
		{
			"ident":"514",
			"name":"ROBERT"
		},
		{
			"ident":"515",
			"name":"AUDREY"
		},
		{
			"ident":"516",
			"name":"RAYMOND"
		},
		{
			"ident":"517",
			"name":"CHRIS"
		},
		{
			"ident":"518",
			"name":"TERRY"
		},
		{
			"ident":"519",
			"name":"KAREN"
		},
		{
			"ident":"520",
			"name":"LOIS"
		},
		{
			"ident":"521",
			"name":"DEBRA"
		},
		{
			"ident":"522",
			"name":"JIMMY"
		},
		{
			"ident":"523",
			"name":"BRANDON"
		},
		{
			"ident":"524",
			"name":"EDITH"
		},
		{
			"ident":"525",
			"name":"LARRY"
		},
		{
			"ident":"526",
			"name":"JULIA"
		},
		{
			"ident":"527",
			"name":"DONALD"
		},
		{
			"ident":"528",
			"name":"JILL"
		},
		{
			"ident":"529",
			"name":"SHERWOOD"
		},
		{
			"ident":"530",
			"name":"KATHERINE"
		},
		{
			"ident":"531",
			"name":"LOUISE"
		},
		{
			"ident":"532",
			"name":"NICHOLAS"
		},
		{
			"ident":"533",
			"name":"CONNIE"
		},
		{
			"ident":"534",
			"name":"RUBEN"
		},
		{
			"ident":"535",
			"name":"ANNE"
		},
		{
			"ident":"536",
			"name":"THELMA"
		},
		{
			"ident":"537",
			"name":"GLADYS"
		},
		{
			"ident":"538",
			"name":"FRANCISCO"
		},
		{
			"ident":"539",
			"name":"RICHARD"
		},
		{
			"ident":"540",
			"name":"JUDY"
		},
		{
			"ident":"541",
			"name":"RONNIE"
		},
		{
			"ident":"542",
			"name":"TITUS"
		},
		{
			"ident":"543",
			"name":"ELLA"
		},
		{
			"ident":"544",
			"name":"LEONARD"
		},
		{
			"ident":"545",
			"name":"MARJORIE"
		},
		{
			"ident":"546",
			"name":"PATRICIA"
		},
		{
			"ident":"547",
			"name":"ANNETTE"
		},
		{
			"ident":"548",
			"name":"WILLIAM"
		},
		{
			"ident":"549",
			"name":"PAMELA"
		},
		{
			"ident":"550",
			"name":"PALMER"
		},
		{
			"ident":"551",
			"name":"CATHERINE"
		},
		{
			"ident":"552",
			"name":"ALICE"
		},
		{
			"ident":"553",
			"name":"RAY"
		},
		{
			"ident":"554",
			"name":"DAVID"
		},
		{
			"ident":"555",
			"name":"PHILIP"
		},
		{
			"ident":"556",
			"name":"RUBY"
		},
		{
			"ident":"557",
			"name":"JAMIE"
		},
		{
			"ident":"558",
			"name":"RITA"
		},
		{
			"ident":"559",
			"name":"MILDRED"
		},
		{
			"ident":"560",
			"name":"SAMANTHA"
		},
		{
			"ident":"561",
			"name":"ANTONIO"
		},
		{
			"ident":"562",
			"name":"ELEANOR"
		},
		{
			"ident":"563",
			"name":"CURTIS"
		},
		{
			"ident":"564",
			"name":"BILLY"
		},
		{
			"ident":"565",
			"name":"ALFRED"
		},
		{
			"ident":"566",
			"name":"JASON"
		},
		{
			"ident":"567",
			"name":"GRACE"
		},
		{
			"ident":"568",
			"name":"BARRY"
		},
		{
			"ident":"569",
			"name":"REGINA"
		},
		{
			"ident":"570",
			"name":"PEGGY"
		},
		{
			"ident":"571",
			"name":"DANA"
		},
		{
			"ident":"572",
			"name":"PEGGY"
		},
		{
			"ident":"573",
			"name":"ELLSWORTH"
		},
		{
			"ident":"574",
			"name":"DEAN"
		},
		{
			"ident":"575",
			"name":"CRYSTAL"
		},
		{
			"ident":"576",
			"name":"BRENT"
		},
		{
			"ident":"577",
			"name":"EDITH"
		},
		{
			"ident":"578",
			"name":"WILMA"
		},
		{
			"ident":"579",
			"name":"CHRIS"
		},
		{
			"ident":"580",
			"name":"BEATRICE"
		},
		{
			"ident":"581",
			"name":"TIFFANY"
		},
		{
			"ident":"582",
			"name":"PHYLLIS"
		},
		{
			"ident":"583",
			"name":"MARILYN"
		},
		{
			"ident":"584",
			"name":"FLORENCE"
		},
		{
			"ident":"585",
			"name":"ELLA"
		},
		{
			"ident":"586",
			"name":"ALICE"
		},
		{
			"ident":"587",
			"name":"IRENE"
		},
		{
			"ident":"588",
			"name":"CARL"
		},
		{
			"ident":"589",
			"name":"KELLY"
		},
		{
			"ident":"590",
			"name":"PAULA"
		},
		{
			"ident":"591",
			"name":"ESTHER"
		},
		{
			"ident":"592",
			"name":"MARJORIE"
		},
		{
			"ident":"593",
			"name":"LESLIE"
		},
		{
			"ident":"594",
			"name":"JACQUELINE"
		},
		{
			"ident":"595",
			"name":"JUNE"
		},
		{
			"ident":"596",
			"name":"SHERRY"
		},
		{
			"ident":"597",
			"name":"SYLVIA"
		},
		{
			"ident":"598",
			"name":"HAROLD"
		},
		{
			"ident":"599",
			"name":"GRACE"
		},
		{
			"ident":"600",
			"name":"BENJAMIN"
		},
		{
			"ident":"601",
			"name":"ALAN"
		},
		{
			"ident":"602",
			"name":"TARA"
		},
		{
			"ident":"603",
			"name":"LYNN"
		},
		{
			"ident":"604",
			"name":"SAMANTHA"
		},
		{
			"ident":"605",
			"name":"DALE"
		},
		{
			"ident":"606",
			"name":"AMBROSE"
		},
		{
			"ident":"607",
			"name":"BRETT"
		},
		{
			"ident":"608",
			"name":"JEREMY"
		},
		{
			"ident":"609",
			"name":"PETER"
		},
		{
			"ident":"610",
			"name":"WILLIAM"
		},
		{
			"ident":"611",
			"name":"JONATHAN"
		},
		{
			"ident":"612",
			"name":"ELLSWORTH"
		},
		{
			"ident":"613",
			"name":"MARK"
		},
		{
			"ident":"614",
			"name":"THERESA"
		},
		{
			"ident":"615",
			"name":"JUDE"
		},
		{
			"ident":"616",
			"name":"HOWARD"
		},
		{
			"ident":"617",
			"name":"NICHOLAS"
		},
		{
			"ident":"618",
			"name":"ANNETTE"
		},
		{
			"ident":"619",
			"name":"CORDELL"
		},
		{
			"ident":"620",
			"name":"KEVIN"
		},
		{
			"ident":"621",
			"name":"ROSE"
		},
		{
			"ident":"622",
			"name":"BONNIE"
		},
		{
			"ident":"623",
			"name":"ANA"
		},
		{
			"ident":"624",
			"name":"GERALD"
		},
		{
			"ident":"625",
			"name":"MELVIN"
		},
		{
			"ident":"626",
			"name":"JOYCE"
		},
		{
			"ident":"627",
			"name":"MARC"
		},
		{
			"ident":"628",
			"name":"ERIN"
		},
		{
			"ident":"629",
			"name":"SAM"
		},
		{
			"ident":"630",
			"name":"DUSTIN"
		},
		{
			"ident":"631",
			"name":"TAMMY"
		},
		{
			"ident":"632",
			"name":"LUCY"
		},
		{
			"ident":"633",
			"name":"BRITT"
		},
		{
			"ident":"634",
			"name":"NATALIE"
		},
		{
			"ident":"635",
			"name":"JULIE"
		},
		{
			"ident":"636",
			"name":"MARTHA"
		},
		{
			"ident":"637",
			"name":"HENRY"
		},
		{
			"ident":"638",
			"name":"FRANCIS"
		},
		{
			"ident":"639",
			"name":"LOUIS"
		},
		{
			"ident":"640",
			"name":"JACQUELINE"
		},
		{
			"ident":"641",
			"name":"SHARON"
		},
		{
			"ident":"642",
			"name":"VALERIE"
		},
		{
			"ident":"643",
			"name":"JEFFREY"
		},
		{
			"ident":"644",
			"name":"JEREMY"
		},
		{
			"ident":"645",
			"name":"ROBERT"
		},
		{
			"ident":"646",
			"name":"PATRICK"
		},
		{
			"ident":"647",
			"name":"JAMIE"
		},
		{
			"ident":"648",
			"name":"EVA"
		},
		{
			"ident":"649",
			"name":"SUZANNE"
		},
		{
			"ident":"650",
			"name":"TITUS"
		},
		{
			"ident":"651",
			"name":"ELLEN"
		},
		{
			"ident":"652",
			"name":"GREG"
		},
		{
			"ident":"653",
			"name":"JANICE"
		},
		{
			"ident":"654",
			"name":"TINA"
		},
		{
			"ident":"655",
			"name":"TOMMY"
		},
		{
			"ident":"656",
			"name":"CHERYL"
		},
		{
			"ident":"657",
			"name":"WENDY"
		},
		{
			"ident":"658",
			"name":"NATALIE"
		},
		{
			"ident":"659",
			"name":"PETER"
		},
		{
			"ident":"660",
			"name":"NATHAN"
		},
		{
			"ident":"661",
			"name":"PHILIP"
		},
		{
			"ident":"662",
			"name":"PAMELA"
		},
		{
			"ident":"663",
			"name":"JUNE"
		},
		{
			"ident":"664",
			"name":"JULIA"
		},
		{
			"ident":"665",
			"name":"JEANNE"
		},
		{
			"ident":"666",
			"name":"ELIZABETH"
		},
		{
			"ident":"667",
			"name":"GLEN"
		},
		{
			"ident":"668",
			"name":"SARAH"
		},
		{
			"ident":"669",
			"name":"ANNE"
		},
		{
			"ident":"670",
			"name":"JASON"
		},
		{
			"ident":"671",
			"name":"BEVERLY"
		},
		{
			"ident":"672",
			"name":"AMY"
		},
		{
			"ident":"673",
			"name":"CLYDE"
		},
		{
			"ident":"674",
			"name":"EILEEN"
		},
		{
			"ident":"675",
			"name":"SALLY"
		},
		{
			"ident":"676",
			"name":"MARGARET"
		},
		{
			"ident":"677",
			"name":"SANDRA"
		},
		{
			"ident":"678",
			"name":"DOLORES"
		},
		{
			"ident":"679",
			"name":"WENDY"
		},
		{
			"ident":"680",
			"name":"SALLY"
		},
		{
			"ident":"681",
			"name":"HEATHER"
		},
		{
			"ident":"682",
			"name":"NANCY"
		},
		{
			"ident":"683",
			"name":"GARY"
		},
		{
			"ident":"684",
			"name":"BRIAN"
		},
		{
			"ident":"685",
			"name":"STANLEY"
		},
		{
			"ident":"686",
			"name":"RICK"
		},
		{
			"ident":"687",
			"name":"MARGARET"
		},
		{
			"ident":"688",
			"name":"JEANNE"
		},
		{
			"ident":"689",
			"name":"EDITH"
		},
		{
			"ident":"690",
			"name":"MICHELLE"
		},
		{
			"ident":"691",
			"name":"JOAN"
		},
		{
			"ident":"692",
			"name":"SHARON"
		},
		{
			"ident":"693",
			"name":"WANDA"
		},
		{
			"ident":"694",
			"name":"KATHRYN"
		},
		{
			"ident":"695",
			"name":"YVONNE"
		},
		{
			"ident":"696",
			"name":"EDNA"
		},
		{
			"ident":"697",
			"name":"LINDA"
		},
		{
			"ident":"698",
			"name":"RICARDO"
		},
		{
			"ident":"699",
			"name":"PAULINE"
		},
		{
			"ident":"700",
			"name":"BETTY"
		},
		{
			"ident":"701",
			"name":"BENEDICT"
		},
		{
			"ident":"702",
			"name":"MARIA"
		},
		{
			"ident":"703",
			"name":"CLARA"
		},
		{
			"ident":"704",
			"name":"PEDRO"
		},
		{
			"ident":"705",
			"name":"JESSIE"
		},
		{
			"ident":"706",
			"name":"IKE"
		},
		{
			"ident":"707",
			"name":"HERBERT"
		},
		{
			"ident":"708",
			"name":"STACY"
		},
		{
			"ident":"709",
			"name":"RACHEL"
		},
		{
			"ident":"710",
			"name":"ANNA"
		},
		{
			"ident":"711",
			"name":"JULIE"
		},
		{
			"ident":"712",
			"name":"VERNON"
		},
		{
			"ident":"713",
			"name":"OSWALDO"
		},
		{
			"ident":"714",
			"name":"TERESA"
		},
		{
			"ident":"715",
			"name":"JOANNE"
		},
		{
			"ident":"716",
			"name":"BERNARD"
		},
		{
			"ident":"717",
			"name":"PHYLLIS"
		},
		{
			"ident":"718",
			"name":"KEVIN"
		},
		{
			"ident":"719",
			"name":"KATHRYN"
		},
		{
			"ident":"720",
			"name":"SHIRLEY"
		},
		{
			"ident":"721",
			"name":"BRETT"
		},
		{
			"ident":"722",
			"name":"CHARLENE"
		},
		{
			"ident":"723",
			"name":"FRANK"
		},
		{
			"ident":"724",
			"name":"RAYMOND"
		},
		{
			"ident":"725",
			"name":"DANIEL"
		},
		{
			"ident":"726",
			"name":"NATHAN"
		},
		{
			"ident":"727",
			"name":"EDITH"
		},
		{
			"ident":"728",
			"name":"TERRY"
		},
		{
			"ident":"729",
			"name":"JASON"
		},
		{
			"ident":"730",
			"name":"CLARENCE"
		},
		{
			"ident":"731",
			"name":"SANDRA"
		},
		{
			"ident":"732",
			"name":"THERESA"
		},
		{
			"ident":"733",
			"name":"JOSEPHINE"
		},
		{
			"ident":"734",
			"name":"TONYA"
		},
		{
			"ident":"735",
			"name":"YVONNE"
		},
		{
			"ident":"736",
			"name":"RICHARD"
		},
		{
			"ident":"737",
			"name":"RODNEY"
		},
		{
			"ident":"738",
			"name":"PATRICIA"
		},
		{
			"ident":"739",
			"name":"GREGORY"
		},
		{
			"ident":"740",
			"name":"VERNON"
		},
		{
			"ident":"741",
			"name":"JERRY"
		},
		{
			"ident":"742",
			"name":"NORMAN"
		},
		{
			"ident":"743",
			"name":"LAURA"
		},
		{
			"ident":"744",
			"name":"BRENDA"
		},
		{
			"ident":"745",
			"name":"MELISSA"
		},
		{
			"ident":"746",
			"name":"CRISTOBAL"
		},
		{
			"ident":"747",
			"name":"VICKI"
		},
		{
			"ident":"748",
			"name":"CHARLENE"
		},
		{
			"ident":"749",
			"name":"ROSEMARY"
		},
		{
			"ident":"750",
			"name":"EDITH"
		},
		{
			"ident":"751",
			"name":"CYNTHIA"
		},
		{
			"ident":"752",
			"name":"ROSE"
		},
		{
			"ident":"753",
			"name":"ROSA"
		},
		{
			"ident":"754",
			"name":"DON"
		},
		{
			"ident":"755",
			"name":"KRISTIN"
		},
		{
			"ident":"756",
			"name":"MARGARET"
		},
		{
			"ident":"757",
			"name":"JAMIE"
		},
		{
			"ident":"758",
			"name":"GEORGE"
		},
		{
			"ident":"759",
			"name":"TIMOTHY"
		},
		{
			"ident":"760",
			"name":"BONNIE"
		},
		{
			"ident":"761",
			"name":"THELMA"
		},
		{
			"ident":"762",
			"name":"JACQUELINE"
		},
		{
			"ident":"763",
			"name":"STANTON"
		},
		{
			"ident":"764",
			"name":"VERNON"
		},
		{
			"ident":"765",
			"name":"LOUIS"
		},
		{
			"ident":"766",
			"name":"MANUEL"
		},
		{
			"ident":"767",
			"name":"GENE"
		},
		{
			"ident":"768",
			"name":"WALTON"
		},
		{
			"ident":"769",
			"name":"RANDALL"
		},
		{
			"ident":"770",
			"name":"AMBER"
		},
		{
			"ident":"771",
			"name":"DANNY"
		},
		{
			"ident":"772",
			"name":"ELEANOR"
		},
		{
			"ident":"773",
			"name":"CARLOS"
		},
		{
			"ident":"774",
			"name":"TIFFANY"
		},
		{
			"ident":"775",
			"name":"JEROME"
		},
		{
			"ident":"776",
			"name":"THERESA"
		},
		{
			"ident":"777",
			"name":"MAURICE"
		},
		{
			"ident":"778",
			"name":"PEGGY"
		},
		{
			"ident":"779",
			"name":"STEVEN"
		},
		{
			"ident":"780",
			"name":"GRACE"
		},
		{
			"ident":"781",
			"name":"GLADYS"
		},
		{
			"ident":"782",
			"name":"SHERWOOD"
		},
		{
			"ident":"783",
			"name":"BARBARA"
		},
		{
			"ident":"784",
			"name":"PHYLLIS"
		},
		{
			"ident":"785",
			"name":"HAROLD"
		},
		{
			"ident":"786",
			"name":"BERTHA"
		},
		{
			"ident":"787",
			"name":"CHARLIE"
		},
		{
			"ident":"788",
			"name":"RICK"
		},
		{
			"ident":"789",
			"name":"DEL"
		},
		{
			"ident":"790",
			"name":"TROY"
		},
		{
			"ident":"791",
			"name":"WALTON"
		},
		{
			"ident":"792",
			"name":"RAYFORD"
		},
		{
			"ident":"793",
			"name":"MONICA"
		},
		{
			"ident":"794",
			"name":"MARILYN"
		},
		{
			"ident":"795",
			"name":"JESSE"
		},
		{
			"ident":"796",
			"name":"JOANNE"
		},
		{
			"ident":"797",
			"name":"ANTHONY"
		},
		{
			"ident":"798",
			"name":"AGNES"
		},
		{
			"ident":"799",
			"name":"FLORENCE"
		},
		{
			"ident":"800",
			"name":"LORI"
		},
		{
			"ident":"801",
			"name":"DANIELLE"
		},
		{
			"ident":"802",
			"name":"PAMELA"
		},
		{
			"ident":"803",
			"name":"LONNY"
		},
		{
			"ident":"804",
			"name":"ANTHONY"
		},
		{
			"ident":"805",
			"name":"WAYNE"
		},
		{
			"ident":"806",
			"name":"DIANE"
		},
		{
			"ident":"807",
			"name":"SAMUEL"
		},
		{
			"ident":"808",
			"name":"BRIAN"
		},
		{
			"ident":"809",
			"name":"TITUS"
		},
		{
			"ident":"810",
			"name":"ELIZABETH"
		},
		{
			"ident":"811",
			"name":"EDNA"
		},
		{
			"ident":"812",
			"name":"CONNIE"
		},
		{
			"ident":"813",
			"name":"CARL"
		},
		{
			"ident":"814",
			"name":"PEGGY"
		},
		{
			"ident":"815",
			"name":"TONEY"
		},
		{
			"ident":"816",
			"name":"DEL"
		},
		{
			"ident":"817",
			"name":"JON"
		},
		{
			"ident":"818",
			"name":"ROSA"
		},
		{
			"ident":"819",
			"name":"JESSE"
		},
		{
			"ident":"820",
			"name":"BRITT"
		},
		{
			"ident":"821",
			"name":"BRIAN"
		},
		{
			"ident":"822",
			"name":"STACEY"
		},
		{
			"ident":"823",
			"name":"MELINDA"
		},
		{
			"ident":"824",
			"name":"ROBIN"
		},
		{
			"ident":"825",
			"name":"JACOB"
		},
		{
			"ident":"826",
			"name":"LYNN"
		},
		{
			"ident":"827",
			"name":"SHIRLEY"
		},
		{
			"ident":"828",
			"name":"RALPH"
		},
		{
			"ident":"829",
			"name":"TERESA"
		},
		{
			"ident":"830",
			"name":"HERBERT"
		},
		{
			"ident":"831",
			"name":"MARION"
		},
		{
			"ident":"832",
			"name":"TERESA"
		},
		{
			"ident":"833",
			"name":"DOUGLAS"
		},
		{
			"ident":"834",
			"name":"RUBY"
		},
		{
			"ident":"835",
			"name":"JON"
		},
		{
			"ident":"836",
			"name":"ETHEL"
		},
		{
			"ident":"837",
			"name":"VALERIE"
		},
		{
			"ident":"838",
			"name":"KENNETH"
		},
		{
			"ident":"839",
			"name":"RHETT"
		},
		{
			"ident":"840",
			"name":"EARL"
		},
		{
			"ident":"841",
			"name":"LEROY"
		},
		{
			"ident":"842",
			"name":"MILDRED"
		},
		{
			"ident":"843",
			"name":"ALICIA"
		},
		{
			"ident":"844",
			"name":"JENNIFER"
		},
		{
			"ident":"845",
			"name":"LEONARD"
		},
		{
			"ident":"846",
			"name":"LAWRENCE"
		},
		{
			"ident":"847",
			"name":"CARLA"
		},
		{
			"ident":"848",
			"name":"GLENN"
		},
		{
			"ident":"849",
			"name":"BERNARD"
		},
		{
			"ident":"850",
			"name":"IKE"
		},
		{
			"ident":"851",
			"name":"ROBERT"
		},
		{
			"ident":"852",
			"name":"GLEN"
		},
		{
			"ident":"853",
			"name":"EMILY"
		},
		{
			"ident":"854",
			"name":"JILL"
		},
		{
			"ident":"855",
			"name":"STEVEN"
		},
		{
			"ident":"856",
			"name":"SHERRY"
		},
		{
			"ident":"857",
			"name":"ANNETTE"
		},
		{
			"ident":"858",
			"name":"CLIFFORD"
		},
		{
			"ident":"859",
			"name":"ZACHARY"
		},
		{
			"ident":"860",
			"name":"DOUGLASS"
		},
		{
			"ident":"861",
			"name":"ROBIN"
		},
		{
			"ident":"862",
			"name":"JOSE"
		},
		{
			"ident":"863",
			"name":"PEGGY"
		},
		{
			"ident":"864",
			"name":"MARIE"
		},
		{
			"ident":"865",
			"name":"CHRISTINA"
		},
		{
			"ident":"866",
			"name":"JUDY"
		},
		{
			"ident":"867",
			"name":"MARTIN"
		},
		{
			"ident":"868",
			"name":"MICHELLE"
		},
		{
			"ident":"869",
			"name":"LONNY"
		},
		{
			"ident":"870",
			"name":"THELMA"
		},
		{
			"ident":"871",
			"name":"JOHNNY"
		},
		{
			"ident":"872",
			"name":"PEGGY"
		},
		{
			"ident":"873",
			"name":"MARGARET"
		},
		{
			"ident":"874",
			"name":"CYNTHIA"
		},
		{
			"ident":"875",
			"name":"DEL"
		},
		{
			"ident":"876",
			"name":"JANET"
		},
		{
			"ident":"877",
			"name":"SHAWN"
		},
		{
			"ident":"878",
			"name":"JOSEPHINE"
		},
		{
			"ident":"879",
			"name":"JAMIE"
		},
		{
			"ident":"880",
			"name":"MILAN"
		},
		{
			"ident":"881",
			"name":"HERMAN"
		},
		{
			"ident":"882",
			"name":"ROGER"
		},
		{
			"ident":"883",
			"name":"EUGENE"
		},
		{
			"ident":"884",
			"name":"ASHLEY"
		},
		{
			"ident":"885",
			"name":"CHARLENE"
		},
		{
			"ident":"886",
			"name":"PAUL"
		},
		{
			"ident":"887",
			"name":"JOHNNY"
		},
		{
			"ident":"888",
			"name":"HONG"
		},
		{
			"ident":"889",
			"name":"CHAD"
		},
		{
			"ident":"890",
			"name":"GENE"
		},
		{
			"ident":"891",
			"name":"DIANA"
		},
		{
			"ident":"892",
			"name":"SUZANNE"
		},
		{
			"ident":"893",
			"name":"JENNIFER"
		},
		{
			"ident":"894",
			"name":"GEORGE"
		},
		{
			"ident":"895",
			"name":"JACK"
		},
		{
			"ident":"896",
			"name":"JENNIFER"
		},
		{
			"ident":"897",
			"name":"KENNETH"
		},
		{
			"ident":"898",
			"name":"CHARLIE"
		},
		{
			"ident":"899",
			"name":"HECTOR"
		},
		{
			"ident":"900",
			"name":"BETH"
		},
		{
			"ident":"901",
			"name":"SHAWN"
		},
		{
			"ident":"902",
			"name":"SALLY"
		},
		{
			"ident":"903",
			"name":"MARIO"
		},
		{
			"ident":"904",
			"name":"RITA"
		},
		{
			"ident":"905",
			"name":"ELSIE"
		},
		{
			"ident":"906",
			"name":"ELLA"
		},
		{
			"ident":"907",
			"name":"BENJAMIN"
		},
		{
			"ident":"908",
			"name":"MILDRED"
		},
		{
			"ident":"909",
			"name":"TOMMY"
		},
		{
			"ident":"910",
			"name":"SHEILA"
		},
		{
			"ident":"911",
			"name":"JASON"
		},
		{
			"ident":"912",
			"name":"ALEX"
		},
		{
			"ident":"913",
			"name":"RONNIE"
		},
		{
			"ident":"914",
			"name":"ELEANOR"
		},
		{
			"ident":"915",
			"name":"HECTOR"
		},
		{
			"ident":"916",
			"name":"DIANA"
		},
		{
			"ident":"917",
			"name":"HERBERT"
		},
		{
			"ident":"918",
			"name":"RITA"
		},
		{
			"ident":"919",
			"name":"RAMON"
		},
		{
			"ident":"920",
			"name":"CURTIS"
		},
		{
			"ident":"921",
			"name":"JEFFREY"
		},
		{
			"ident":"922",
			"name":"ESTHER"
		},
		{
			"ident":"923",
			"name":"BARBARA"
		},
		{
			"ident":"924",
			"name":"MIGUEL"
		},
		{
			"ident":"925",
			"name":"ALEX"
		},
		{
			"ident":"926",
			"name":"BRENDA"
		},
		{
			"ident":"927",
			"name":"SHIRLEY"
		},
		{
			"ident":"928",
			"name":"DEREK"
		},
		{
			"ident":"929",
			"name":"RYAN"
		},
		{
			"ident":"930",
			"name":"CAROL"
		},
		{
			"ident":"931",
			"name":"DUSTIN"
		},
		{
			"ident":"932",
			"name":"ANGELA"
		},
		{
			"ident":"933",
			"name":"JEREMY"
		},
		{
			"ident":"934",
			"name":"LOIS"
		},
		{
			"ident":"935",
			"name":"SYLVIA"
		},
		{
			"ident":"936",
			"name":"MARC"
		},
		{
			"ident":"937",
			"name":"ROBERT"
		},
		{
			"ident":"938",
			"name":"CAROL"
		},
		{
			"ident":"939",
			"name":"SUE"
		},
		{
			"ident":"940",
			"name":"CONNIE"
		},
		{
			"ident":"941",
			"name":"MARIE"
		},
		{
			"ident":"942",
			"name":"JEROME"
		},
		{
			"ident":"943",
			"name":"GERALD"
		},
		{
			"ident":"944",
			"name":"ANITA"
		},
		{
			"ident":"945",
			"name":"KIM"
		},
		{
			"ident":"946",
			"name":"DARLENE"
		},
		{
			"ident":"947",
			"name":"VALERIE"
		},
		{
			"ident":"948",
			"name":"ROSEMARY"
		},
		{
			"ident":"949",
			"name":"JERRY"
		},
		{
			"ident":"950",
			"name":"KELLY"
		},
		{
			"ident":"951",
			"name":"PATRICIA"
		},
		{
			"ident":"952",
			"name":"ERIN"
		},
		{
			"ident":"953",
			"name":"ANGELA"
		},
		{
			"ident":"954",
			"name":"LARRY"
		},
		{
			"ident":"955",
			"name":"MIGUEL"
		},
		{
			"ident":"956",
			"name":"DENISE"
		},
		{
			"ident":"957",
			"name":"TONYA"
		},
		{
			"ident":"958",
			"name":"OSCAR"
		},
		{
			"ident":"959",
			"name":"VERONICA"
		},
		{
			"ident":"960",
			"name":"BRETT"
		},
		{
			"ident":"961",
			"name":"TERRI"
		},
		{
			"ident":"962",
			"name":"LUIS"
		},
		{
			"ident":"963",
			"name":"HAROLD"
		},
		{
			"ident":"964",
			"name":"SARAH"
		},
		{
			"ident":"965",
			"name":"GARY"
		},
		{
			"ident":"966",
			"name":"MARY"
		},
		{
			"ident":"967",
			"name":"WILMA"
		},
		{
			"ident":"968",
			"name":"MONICA"
		},
		{
			"ident":"969",
			"name":"FREDERICK"
		},
		{
			"ident":"970",
			"name":"LLOYD"
		},
		{
			"ident":"971",
			"name":"SHARON"
		},
		{
			"ident":"972",
			"name":"AUDREY"
		},
		{
			"ident":"973",
			"name":"ROSEMARY"
		},
		{
			"ident":"974",
			"name":"YVONNE"
		},
		{
			"ident":"975",
			"name":"PEARL"
		},
		{
			"ident":"976",
			"name":"JERRY"
		},
		{
			"ident":"977",
			"name":"DOLORES"
		},
		{
			"ident":"978",
			"name":"JOSEPH"
		},
		{
			"ident":"979",
			"name":"RAYMOND"
		},
		{
			"ident":"980",
			"name":"DALE"
		},
		{
			"ident":"981",
			"name":"MEGAN"
		},
		{
			"ident":"982",
			"name":"TOMMY"
		},
		{
			"ident":"983",
			"name":"JULIE"
		},
		{
			"ident":"984",
			"name":"SUSAN"
		},
		{
			"ident":"985",
			"name":"LEE"
		},
		{
			"ident":"986",
			"name":"NANCY"
		},
		{
			"ident":"987",
			"name":"DOLORES"
		},
		{
			"ident":"988",
			"name":"KENNETH"
		},
		{
			"ident":"989",
			"name":"NATALIE"
		},
		{
			"ident":"990",
			"name":"DEBORAH"
		},
		{
			"ident":"991",
			"name":"ELEANOR"
		},
		{
			"ident":"992",
			"name":"MATTHEW"
		},
		{
			"ident":"993",
			"name":"CINDY"
		},
		{
			"ident":"994",
			"name":"EDNA"
		},
		{
			"ident":"995",
			"name":"WILMA"
		},
		{
			"ident":"996",
			"name":"JOANNE"
		},
		{
			"ident":"997",
			"name":"KATHLEEN"
		},
		{
			"ident":"998",
			"name":"CRYSTAL"
		},
		{
			"ident":"999",
			"name":"CRISTOBAL"
		},
		{
			"ident":"1000",
			"name":"JUDY"
		}
	]
}